LICENSE
MANIFEST.in
README.md
setup.py
RugGray.egg-info/PKG-INFO
RugGray.egg-info/SOURCES.txt
RugGray.egg-info/dependency_links.txt
RugGray.egg-info/top_level.txt
ruggray.egg-info/PKG-INFO
ruggray.egg-info/SOURCES.txt
ruggray.egg-info/dependency_links.txt
ruggray.egg-info/top_level.txt
src/ruggray.py