Metadata-Version: 2.1
Name: ruggray
Version: 0.99.3
Summary: Opensesame Forms theme for the University of Groningen
Home-page: https://github.com/markspan/ruggray
Author: Mark Span (primary developer)
Author-email: m.m.span@rug.nl
License: UNKNOWN
Platform: UNKNOWN
Classifier: Intended Audience :: Science/Research
Classifier: Topic :: Scientific/Engineering
Classifier: Environment :: MacOS X
Classifier: Environment :: Win32 (MS Windows)
Classifier: Environment :: X11 Applications
Classifier: License :: OSI Approved :: Apache Software License
Classifier: Programming Language :: Python :: 3
Requires-Python: >=3.6
License-File: LICENSE
